[
  {
    "name": "Fauzi Ramdani",
    "phoneNumber": "sdf",
    "email": "sdfadfads@gg.com",
    "address": "sdf"
  },
  {
    "name": "sdfdsf",
    "phoneNumber": "dsfsaadsfds",
    "email": "adsfasf@sdf.co",
    "address": "sadfasd"
  },
  {
    "name": "fsdafad",
    "phoneNumber": "sdfsdafds",
    "email": "adfsfsd@gfd.co",
    "address": "afdsfads"
  },
  {
    "name": "asdfdsf",
    "phoneNumber": "sadfsadf",
    "email": "dfasfasd@gmail.com",
    "address": "sdfasdf"
  },
  {
    "name": "SDFASDF",
    "phoneNumber": "ADFSDF",
    "email": "apawnibos@gmail.com",
    "address": "ASF"
  },
  {
    "name": "Fauzi Ramdani",
    "phoneNumber": "0895337732828",
    "email": "apawnibos@gmail.com",
    "address": "asdf"
  },
  {
    "name": "sdasf",
    "phoneNumber": "dfasdfsa",
    "email": "sdfdsaf@ksd.com",
    "address": "sdfads"
  },
  {
    "name": "Fauzi Ramdani",
    "phoneNumber": "sdf",
    "email": "sdfadfads@gg.com",
    "address": "sdf"
  },
  {
    "name": "sdfs",
    "phoneNumber": "dsfasdf",
    "email": "sdfadfads@gg.com",
    "address": "sdafsdf"
  },
  {
    "name": "Fauzi Ramdani",
    "phoneNumber": "0895337732828",
    "email": "fauziramdhan38@gmail.com",
    "address": "sdf"
  }
]